[
  {
    "category": "일반상식",
    "difficulty": "normal",
    "id": "gen_normal_001",
    "question": "세계 3대 영화제에 해당하지 않는 것은?",
    "options": ["칸 영화제", "베네치아 영화제", "베를린 국제 영화제", "선댄스 영화제"],
    "answer": 3,
    "explanation": "세계 3대 영화제는 칸(프랑스)·베네치아(이탈리아)·베를린(독일) 영화제입니다. 선댄스는 미국의 독립영화제입니다.",
    "option_explanations": [
      "칸 영화제는 세계 3대 영화제 중 하나입니다.",
      "베네치아 영화제는 세계 3대 영화제 중 하나입니다.",
      "베를린 국제 영화제는 세계 3대 영화제 중 하나입니다.",
      "선댄스 영화제는 미국의 유명 독립영화제이지만 세계 3대 영화제는 아닙니다."
    ]
  },
  {
    "category": "일반상식",
    "difficulty": "normal",
    "id": "gen_normal_002",
    "question": "퓰리처상을 시상하는 분야가 아닌 것은?",
    "options": ["저널리즘", "문학", "음악", "영화"],
    "answer": 3,
    "explanation": "퓰리처상은 저널리즘·문학·음악 분야에 시상하며, 영화 부문은 포함되지 않습니다.",
    "option_explanations": [
      "저널리즘은 퓰리처상의 주요 시상 분야입니다.",
      "문학(소설, 희곡 등)은 퓰리처상 시상 분야입니다.",
      "음악은 퓰리처상 시상 분야 중 하나입니다.",
      "영화는 퓰리처상 시상 분야에 포함되지 않습니다."
    ]
  },
  {
    "category": "일반상식",
    "difficulty": "normal",
    "id": "gen_normal_003",
    "question": "세계보건기구(WHO)의 본부가 위치한 도시는?",
    "options": ["뉴욕", "브뤼셀", "제네바", "런던"],
    "answer": 2,
    "explanation": "세계보건기구(WHO)의 본부는 스위스 제네바에 위치합니다.",
    "option_explanations": [
      "뉴욕에는 유엔(UN) 본부가 위치합니다.",
      "브뤼셀에는 NATO 본부와 EU 주요 기관이 위치합니다.",
      "세계보건기구(WHO) 본부는 스위스 제네바에 있습니다.",
      "런던에는 국제해사기구(IMO) 등이 있습니다."
    ]
  },
  {
    "category": "일반상식",
    "difficulty": "normal",
    "id": "gen_normal_004",
    "question": "인터넷을 발명한 것으로 알려진 '월드 와이드 웹(WWW)'의 창시자는?",
    "options": ["스티브 잡스", "빌 게이츠", "팀 버너스리", "빈트 서프"],
    "answer": 2,
    "explanation": "팀 버너스리는 1989년 월드 와이드 웹(WWW)을 제안하고 HTML·HTTP·URL 개념을 개발하였습니다.",
    "option_explanations": [
      "스티브 잡스는 애플의 공동 창업자로 매킨토시·아이폰 등을 개발했습니다.",
      "빌 게이츠는 마이크로소프트 공동 창업자로 MS-DOS·윈도우를 개발했습니다.",
      "팀 버너스리는 1989년 월드 와이드 웹을 제안한 발명가입니다.",
      "빈트 서프는 인터넷 프로토콜(TCP/IP)을 공동 개발한 '인터넷의 아버지'입니다."
    ]
  },
  {
    "category": "일반상식",
    "difficulty": "normal",
    "id": "gen_normal_005",
    "question": "노벨 평화상 시상식이 열리는 도시는?",
    "options": ["스톡홀름", "오슬로", "코펜하겐", "헬싱키"],
    "answer": 1,
    "explanation": "노벨 평화상은 노르웨이 오슬로에서 시상하며, 나머지 5개 분야는 스웨덴 스톡홀름에서 시상합니다.",
    "option_explanations": [
      "스톡홀름은 물리학·화학·생리의학·문학·경제학상 시상지입니다.",
      "노벨 평화상은 노르웨이 오슬로에서 시상됩니다.",
      "코펜하겐은 덴마크의 수도로 노벨상 시상과 관련이 없습니다.",
      "헬싱키는 핀란드의 수도로 노벨상 시상과 관련이 없습니다."
    ]
  },
  {
    "category": "일반상식",
    "difficulty": "normal",
    "id": "gen_normal_006",
    "question": "국제적십자위원회(ICRC)의 본부가 있는 도시는?",
    "options": ["뉴욕", "제네바", "파리", "비엔나"],
    "answer": 1,
    "explanation": "국제적십자위원회(ICRC)는 1863년 스위스 제네바에서 창설되었으며 본부도 제네바에 있습니다.",
    "option_explanations": [
      "뉴욕에는 유엔 본부가 있습니다.",
      "ICRC 본부는 스위스 제네바에 있습니다.",
      "파리는 유네스코(UNESCO) 본부가 있는 도시입니다.",
      "비엔나에는 국제원자력기구(IAEA) 본부가 있습니다."
    ]
  },
  {
    "category": "일반상식",
    "difficulty": "normal",
    "id": "gen_normal_007",
    "question": "농구 경기에서 한 팀의 선수는 몇 명인가요?",
    "options": ["4명", "5명", "6명", "7명"],
    "answer": 1,
    "explanation": "농구 경기는 팀당 5명이 코트에 출전하며, 벤치 선수를 포함하면 최대 12~15명이 등록됩니다.",
    "option_explanations": [
      "4명은 농구 한 팀의 코트 인원이 아닙니다.",
      "농구는 팀당 5명이 코트에서 경기합니다.",
      "6명은 배구 한 팀의 코트 인원입니다.",
      "7명은 수구 한 팀의 코트 인원입니다."
    ]
  },
  {
    "category": "일반상식",
    "difficulty": "normal",
    "id": "gen_normal_008",
    "question": "세계에서 가장 많이 사용되는 언어(모국어 화자 기준)는?",
    "options": ["영어", "힌디어", "스페인어", "중국어(만다린)"],
    "answer": 3,
    "explanation": "중국어(만다린)는 모국어 화자 기준 약 9억 2천만 명으로 세계에서 가장 많이 사용되는 언어입니다.",
    "option_explanations": [
      "영어는 모국어 화자 약 3억 7천만 명이지만 제2언어 사용자를 합치면 세계 1위입니다.",
      "힌디어는 모국어 화자 약 6억 명입니다.",
      "스페인어는 모국어 화자 약 4억 8천만 명입니다.",
      "중국어(만다린)는 모국어 화자 약 9억 2천만 명으로 세계 1위입니다."
    ]
  },
  {
    "category": "일반상식",
    "difficulty": "normal",
    "id": "gen_normal_009",
    "question": "피카소의 대표작 「게르니카」는 어느 사건을 주제로 한 작품인가요?",
    "options": ["제1차 세계대전", "러시아 혁명", "스페인 내전 중 게르니카 폭격", "제2차 세계대전"],
    "answer": 2,
    "explanation": "「게르니카」(1937)는 스페인 내전 중 나치 독일이 바스크 지방 게르니카 마을을 폭격한 사건을 고발한 작품입니다.",
    "option_explanations": [
      "제1차 세계대전은 1914~1918년으로, 게르니카 제작(1937)과 시기가 다릅니다.",
      "러시아 혁명(1917)은 게르니카의 주제가 아닙니다.",
      "「게르니카」는 1937년 스페인 내전 중 게르니카 마을 폭격을 주제로 한 작품입니다.",
      "제2차 세계대전은 1939~1945년으로, 게르니카 제작(1937) 이후입니다."
    ]
  },
  {
    "category": "일반상식",
    "difficulty": "normal",
    "id": "gen_normal_010",
    "question": "스마트폰 운영 체제 중 구글이 개발한 것은?",
    "options": ["iOS", "Android", "HarmonyOS", "Windows Mobile"],
    "answer": 1,
    "explanation": "Android(안드로이드)는 구글이 인수·개발한 스마트폰 운영 체제로 세계에서 가장 많이 사용됩니다.",
    "option_explanations": [
      "iOS는 애플이 개발한 iPhone용 운영 체제입니다.",
      "Android는 구글이 개발한 스마트폰 운영 체제입니다.",
      "HarmonyOS는 중국 화웨이가 개발한 운영 체제입니다.",
      "Windows Mobile은 마이크로소프트가 개발했으나 현재는 단종된 운영 체제입니다."
    ]
  }
]
